{
  "warnings": [
    {
      "file": "/Users/lchen/kin-ios/KinUX/KinUX/Src/Navigation/KinNavigationController.swift",
      "line": 12,
      "symbol": "KinNavigationController",
      "symbol_kind": "source.lang.swift.decl.class",
      "warning": "undocumented"
    },
    {
      "file": "/Users/lchen/kin-ios/KinUX/KinUX/Src/Navigation/KinNavigationController.swift",
      "line": 14,
      "symbol": "KinNavigationController.viewDidLoad()",
      "symbol_kind": "source.lang.swift.decl.function.method.instance",
      "warning": "undocumented"
    },
    {
      "file": "/Users/lchen/kin-ios/KinUX/KinUX/Src/PaymentFlow/PaymentFlowController.swift",
      "line": 12,
      "symbol": "PaymentFlowController",
      "symbol_kind": "source.lang.swift.decl.class",
      "warning": "undocumented"
    },
    {
      "file": "/Users/lchen/kin-ios/KinUX/KinUX/Src/PaymentFlow/PaymentFlowController.swift",
      "line": 18,
      "symbol": "PaymentFlowController.init(kinAccountContext:hostViewController:)",
      "symbol_kind": "source.lang.swift.decl.function.method.instance",
      "warning": "undocumented"
    },
    {
      "file": "/Users/lchen/kin-ios/KinUX/KinUX/Src/PaymentFlow/PaymentFlowController.swift",
      "line": 24,
      "symbol": "PaymentFlowController.confirmPaymentOfInvoice(_:payerAccount:processingAppInfo:onResult:)",
      "symbol_kind": "source.lang.swift.decl.function.method.instance",
      "warning": "undocumented"
    },
    {
      "file": "/Users/lchen/kin-ios/KinUX/KinUX/Src/PaymentFlow/PaymentFlowViewController.swift",
      "line": 14,
      "symbol": "PaymentFlowViewController",
      "symbol_kind": "source.lang.swift.decl.class",
      "warning": "undocumented"
    },
    {
      "file": "/Users/lchen/kin-ios/KinUX/KinUX/Src/PaymentFlow/PaymentFlowViewController.swift",
      "line": 20,
      "symbol": "PaymentFlowViewController.resultCallback",
      "symbol_kind": "source.lang.swift.decl.var.instance",
      "warning": "undocumented"
    },
    {
      "file": "/Users/lchen/kin-ios/KinUX/KinUX/Src/PaymentFlow/PaymentFlowViewController.swift",
      "line": 22,
      "symbol": "PaymentFlowViewController.init()",
      "symbol_kind": "source.lang.swift.decl.function.method.instance",
      "warning": "undocumented"
    },
    {
      "file": "/Users/lchen/kin-ios/KinUX/KinUX/Src/PaymentFlow/PaymentFlowViewController.swift",
      "line": 30,
      "symbol": "PaymentFlowViewController.attachViewModel(_:)",
      "symbol_kind": "source.lang.swift.decl.function.method.instance",
      "warning": "undocumented"
    },
    {
      "file": "/Users/lchen/kin-ios/KinUX/KinUX/Src/PaymentFlow/PaymentFlowViewController.swift",
      "line": 34,
      "symbol": "PaymentFlowViewController.viewDidLoad()",
      "symbol_kind": "source.lang.swift.decl.function.method.instance",
      "warning": "undocumented"
    },
    {
      "file": "/Users/lchen/kin-ios/KinUX/KinUX/Src/PaymentFlow/PaymentFlowViewController.swift",
      "line": 71,
      "symbol": "PaymentFlowViewController.viewWillLayoutSubviews()",
      "symbol_kind": "source.lang.swift.decl.function.method.instance",
      "warning": "undocumented"
    },
    {
      "file": "/Users/lchen/kin-ios/KinUX/KinUX/Src/PaymentFlow/PaymentFlowViewController.swift",
      "line": 79,
      "symbol": "PaymentFlowViewController",
      "symbol_kind": "source.lang.swift.decl.extension",
      "warning": "undocumented"
    },
    {
      "file": "/Users/lchen/kin-ios/KinUX/KinUX/Src/PaymentFlow/PaymentFlowViewController.swift",
      "line": 80,
      "symbol": "PaymentFlowViewController.paymentConfirmationPayNowTapped()",
      "symbol_kind": "source.lang.swift.decl.function.method.instance",
      "warning": "undocumented"
    },
    {
      "file": "/Users/lchen/kin-ios/KinUX/KinUX/Src/PaymentFlow/PaymentFlowViewController.swift",
      "line": 84,
      "symbol": "PaymentFlowViewController.paymentConfirmationCancelTapped()",
      "symbol_kind": "source.lang.swift.decl.function.method.instance",
      "warning": "undocumented"
    },
    {
      "file": "/Users/lchen/kin-ios/KinUX/KinUX/Src/PaymentFlow/PaymentFlowViewController.swift",
      "line": 90,
      "symbol": "PaymentFlowViewController.paymentConfirmationCloseTapped()",
      "symbol_kind": "source.lang.swift.decl.function.method.instance",
      "warning": "undocumented"
    },
    {
      "file": "/Users/lchen/kin-ios/KinUX/KinUX/Src/PaymentFlow/PaymentFlowViewModel.swift",
      "line": 12,
      "symbol": "PaymentFlowViewModel",
      "symbol_kind": "source.lang.swift.decl.class",
      "warning": "undocumented"
    },
    {
      "file": "/Users/lchen/kin-ios/KinUX/KinUX/Src/PaymentFlow/PaymentFlowViewModel.swift",
      "line": 19,
      "symbol": "PaymentFlowViewModel.init(navigator:args:kinAccountContext:)",
      "symbol_kind": "source.lang.swift.decl.function.method.instance",
      "warning": "undocumented"
    },
    {
      "file": "/Users/lchen/kin-ios/KinUX/KinUX/Src/PaymentFlow/PaymentFlowViewModel.swift",
      "line": 31,
      "symbol": "PaymentFlowViewModel.getDefaultState()",
      "symbol_kind": "source.lang.swift.decl.function.method.instance",
      "warning": "undocumented"
    },
    {
      "file": "/Users/lchen/kin-ios/KinUX/KinUX/Src/PaymentFlow/PaymentFlowViewModel.swift",
      "line": 35,
      "symbol": "PaymentFlowViewModel.onStateUpdated(_:)",
      "symbol_kind": "source.lang.swift.decl.function.method.instance",
      "warning": "undocumented"
    },
    {
      "file": "/Users/lchen/kin-ios/KinUX/KinUX/Src/PaymentFlow/PaymentFlowViewModel.swift",
      "line": 57,
      "symbol": "PaymentFlowViewModel.listenerReady()",
      "symbol_kind": "source.lang.swift.decl.function.method.instance",
      "warning": "undocumented"
    },
    {
      "file": "/Users/lchen/kin-ios/KinUX/KinUX/Src/PaymentFlow/PaymentFlowViewModel.swift",
      "line": 66,
      "symbol": "PaymentFlowViewModel.onCancelTapped(onCompleted:)",
      "symbol_kind": "source.lang.swift.decl.function.method.instance",
      "warning": "undocumented"
    },
    {
      "file": "/Users/lchen/kin-ios/KinUX/KinUX/Src/PaymentFlow/PaymentFlowViewModel.swift",
      "line": 71,
      "symbol": "PaymentFlowViewModel.onConfirmTapped()",
      "symbol_kind": "source.lang.swift.decl.function.method.instance",
      "warning": "undocumented"
    },
    {
      "file": "/Users/lchen/kin-ios/KinUX/KinUX/Src/PaymentFlow/PaymentFlowViewModelType.swift",
      "line": 12,
      "symbol": "PaymentFlowViewModelArgs",
      "symbol_kind": "source.lang.swift.decl.struct",
      "warning": "undocumented"
    },
    {
      "file": "/Users/lchen/kin-ios/KinUX/KinUX/Src/PaymentFlow/PaymentFlowViewModelType.swift",
      "line": 13,
      "symbol": "PaymentFlowViewModelArgs.invoice",
      "symbol_kind": "source.lang.swift.decl.var.instance",
      "warning": "undocumented"
    },
    {
      "file": "/Users/lchen/kin-ios/KinUX/KinUX/Src/PaymentFlow/PaymentFlowViewModelType.swift",
      "line": 14,
      "symbol": "PaymentFlowViewModelArgs.payerAccountId",
      "symbol_kind": "source.lang.swift.decl.var.instance",
      "warning": "undocumented"
    },
    {
      "file": "/Users/lchen/kin-ios/KinUX/KinUX/Src/PaymentFlow/PaymentFlowViewModelType.swift",
      "line": 15,
      "symbol": "PaymentFlowViewModelArgs.appInfo",
      "symbol_kind": "source.lang.swift.decl.var.instance",
      "warning": "undocumented"
    },
    {
      "file": "/Users/lchen/kin-ios/KinUX/KinUX/Src/PaymentFlow/PaymentFlowViewModelType.swift",
      "line": 18,
      "symbol": "PaymentFlowViewModelState",
      "symbol_kind": "source.lang.swift.decl.enum",
      "warning": "undocumented"
    },
    {
      "file": "/Users/lchen/kin-ios/KinUX/KinUX/Src/PaymentFlow/PaymentFlowViewModelType.swift",
      "line": 19,
      "symbol": "PaymentFlowViewModelState.init",
      "symbol_kind": "source.lang.swift.decl.enumelement",
      "warning": "undocumented"
    },
    {
      "file": "/Users/lchen/kin-ios/KinUX/KinUX/Src/PaymentFlow/PaymentFlowViewModelType.swift",
      "line": 20,
      "symbol": "PaymentFlowViewModelState.confirmation(appIcon:amount:appName:newBalanceAfter:)",
      "symbol_kind": "source.lang.swift.decl.enumelement",
      "warning": "undocumented"
    },
    {
      "file": "/Users/lchen/kin-ios/KinUX/KinUX/Src/PaymentFlow/PaymentFlowViewModelType.swift",
      "line": 21,
      "symbol": "PaymentFlowViewModelState.processing",
      "symbol_kind": "source.lang.swift.decl.enumelement",
      "warning": "undocumented"
    },
    {
      "file": "/Users/lchen/kin-ios/KinUX/KinUX/Src/PaymentFlow/PaymentFlowViewModelType.swift",
      "line": 22,
      "symbol": "PaymentFlowViewModelState.succes(transactionHash:)",
      "symbol_kind": "source.lang.swift.decl.enumelement",
      "warning": "undocumented"
    },
    {
      "file": "/Users/lchen/kin-ios/KinUX/KinUX/Src/PaymentFlow/PaymentFlowViewModelType.swift",
      "line": 23,
      "symbol": "PaymentFlowViewModelState.error(error:balance:)",
      "symbol_kind": "source.lang.swift.decl.enumelement",
      "warning": "undocumented"
    },
    {
      "file": "/Users/lchen/kin-ios/KinUX/KinUX/Src/PaymentFlow/PaymentFlowViewModelType.swift",
      "line": 24,
      "symbol": "PaymentFlowViewModelState.closed",
      "symbol_kind": "source.lang.swift.decl.enumelement",
      "warning": "undocumented"
    },
    {
      "file": "/Users/lchen/kin-ios/KinUX/KinUX/Src/PaymentFlow/PaymentFlowViewModelType.swift",
      "line": 27,
      "symbol": "PaymentFlowViewModelResult",
      "symbol_kind": "source.lang.swift.decl.enum",
      "warning": "undocumented"
    },
    {
      "file": "/Users/lchen/kin-ios/KinUX/KinUX/Src/PaymentFlow/PaymentFlowViewModelType.swift",
      "line": 28,
      "symbol": "PaymentFlowViewModelResult.success(transactionHash:)",
      "symbol_kind": "source.lang.swift.decl.enumelement",
      "warning": "undocumented"
    },
    {
      "file": "/Users/lchen/kin-ios/KinUX/KinUX/Src/PaymentFlow/PaymentFlowViewModelType.swift",
      "line": 29,
      "symbol": "PaymentFlowViewModelResult.failure(error:)",
      "symbol_kind": "source.lang.swift.decl.enumelement",
      "warning": "undocumented"
    },
    {
      "file": "/Users/lchen/kin-ios/KinUX/KinUX/Src/PaymentFlow/PaymentFlowViewModelType.swift",
      "line": 32,
      "symbol": "PaymentFlowError",
      "symbol_kind": "source.lang.swift.decl.struct",
      "warning": "undocumented"
    },
    {
      "file": "/Users/lchen/kin-ios/KinUX/KinUX/Src/PaymentFlow/PaymentFlowViewModelType.swift",
      "line": 36,
      "symbol": "PaymentFlowError.withReason(_:)",
      "symbol_kind": "source.lang.swift.decl.function.method.static",
      "warning": "undocumented"
    },
    {
      "file": "/Users/lchen/kin-ios/KinUX/KinUX/Src/PaymentFlow/PaymentFlowViewModelType.swift",
      "line": 41,
      "symbol": "PaymentFlowError.fromError(_:)",
      "symbol_kind": "source.lang.swift.decl.function.method.static",
      "warning": "undocumented"
    },
    {
      "file": "/Users/lchen/kin-ios/KinUX/KinUX/Src/PaymentFlow/PaymentFlowViewModelType.swift",
      "line": 47,
      "symbol": "PaymentFlowFailureReason",
      "symbol_kind": "source.lang.swift.decl.enum",
      "warning": "undocumented"
    },
    {
      "file": "/Users/lchen/kin-ios/KinUX/KinUX/Src/PaymentFlow/PaymentFlowViewModelType.swift",
      "line": 48,
      "symbol": "PaymentFlowFailureReason.errorMessage",
      "symbol_kind": "source.lang.swift.decl.enumelement",
      "warning": "undocumented"
    },
    {
      "file": "/Users/lchen/kin-ios/KinUX/KinUX/Src/PaymentFlow/PaymentFlowViewModelType.swift",
      "line": 49,
      "symbol": "PaymentFlowFailureReason.canceled",
      "symbol_kind": "source.lang.swift.decl.enumelement",
      "warning": "undocumented"
    },
    {
      "file": "/Users/lchen/kin-ios/KinUX/KinUX/Src/PaymentFlow/PaymentFlowViewModelType.swift",
      "line": 50,
      "symbol": "PaymentFlowFailureReason.alreadyPurchased",
      "symbol_kind": "source.lang.swift.decl.enumelement",
      "warning": "undocumented"
    },
    {
      "file": "/Users/lchen/kin-ios/KinUX/KinUX/Src/PaymentFlow/PaymentFlowViewModelType.swift",
      "line": 51,
      "symbol": "PaymentFlowFailureReason.unknownFailure",
      "symbol_kind": "source.lang.swift.decl.enumelement",
      "warning": "undocumented"
    },
    {
      "file": "/Users/lchen/kin-ios/KinUX/KinUX/Src/PaymentFlow/PaymentFlowViewModelType.swift",
      "line": 52,
      "symbol": "PaymentFlowFailureReason.unknownInvoice",
      "symbol_kind": "source.lang.swift.decl.enumelement",
      "warning": "undocumented"
    },
    {
      "file": "/Users/lchen/kin-ios/KinUX/KinUX/Src/PaymentFlow/PaymentFlowViewModelType.swift",
      "line": 53,
      "symbol": "PaymentFlowFailureReason.unknownPayerAccount",
      "symbol_kind": "source.lang.swift.decl.enumelement",
      "warning": "undocumented"
    },
    {
      "file": "/Users/lchen/kin-ios/KinUX/KinUX/Src/PaymentFlow/PaymentFlowViewModelType.swift",
      "line": 54,
      "symbol": "PaymentFlowFailureReason.insufficientBalance",
      "symbol_kind": "source.lang.swift.decl.enumelement",
      "warning": "undocumented"
    },
    {
      "file": "/Users/lchen/kin-ios/KinUX/KinUX/Src/PaymentFlow/PaymentFlowViewModelType.swift",
      "line": 55,
      "symbol": "PaymentFlowFailureReason.misconfiguredRequest",
      "symbol_kind": "source.lang.swift.decl.enumelement",
      "warning": "undocumented"
    },
    {
      "file": "/Users/lchen/kin-ios/KinUX/KinUX/Src/PaymentFlow/PaymentFlowViewModelType.swift",
      "line": 56,
      "symbol": "PaymentFlowFailureReason.deniedByService",
      "symbol_kind": "source.lang.swift.decl.enumelement",
      "warning": "undocumented"
    },
    {
      "file": "/Users/lchen/kin-ios/KinUX/KinUX/Src/PaymentFlow/PaymentFlowViewModelType.swift",
      "line": 57,
      "symbol": "PaymentFlowFailureReason.sdkUpgradeRequired",
      "symbol_kind": "source.lang.swift.decl.enumelement",
      "warning": "undocumented"
    },
    {
      "file": "/Users/lchen/kin-ios/KinUX/KinUX/Src/PaymentFlow/PaymentFlowViewModelType.swift",
      "line": 58,
      "symbol": "PaymentFlowFailureReason.badNetwork",
      "symbol_kind": "source.lang.swift.decl.enumelement",
      "warning": "undocumented"
    },
    {
      "file": "/Users/lchen/kin-ios/KinUX/KinUX/Src/PaymentFlow/PaymentFlowViewModelType.swift",
      "line": 61,
      "symbol": "PaymentFlowViewModelType",
      "symbol_kind": "source.lang.swift.decl.protocol",
      "warning": "undocumented"
    },
    {
      "file": "/Users/lchen/kin-ios/KinUX/KinUX/Src/PaymentFlow/PaymentFlowViewModelType.swift",
      "line": 63,
      "symbol": "PaymentFlowViewModelType.listenerReady()",
      "symbol_kind": "source.lang.swift.decl.function.method.instance",
      "warning": "undocumented"
    },
    {
      "file": "/Users/lchen/kin-ios/KinUX/KinUX/Src/PaymentFlow/PaymentFlowViewModelType.swift",
      "line": 65,
      "symbol": "PaymentFlowViewModelType.onCancelTapped(onCompleted:)",
      "symbol_kind": "source.lang.swift.decl.function.method.instance",
      "warning": "undocumented"
    },
    {
      "file": "/Users/lchen/kin-ios/KinUX/KinUX/Src/PaymentFlow/PaymentFlowViewModelType.swift",
      "line": 67,
      "symbol": "PaymentFlowViewModelType.onConfirmTapped()",
      "symbol_kind": "source.lang.swift.decl.function.method.instance",
      "warning": "undocumented"
    },
    {
      "file": "/Users/lchen/kin-ios/KinUX/KinUX/Src/Presentation/KinPresentationController.swift",
      "line": 11,
      "symbol": "SheetTransitionCover",
      "symbol_kind": "source.lang.swift.decl.enum",
      "warning": "undocumented"
    },
    {
      "file": "/Users/lchen/kin-ios/KinUX/KinUX/Src/Presentation/KinPresentationController.swift",
      "line": 14,
      "symbol": "SheetTransitionCover.custom(height:)",
      "symbol_kind": "source.lang.swift.decl.enumelement",
      "warning": "undocumented"
    },
    {
      "file": "/Users/lchen/kin-ios/KinUX/KinUX/Src/Presentation/KinPresentationController.swift",
      "line": 15,
      "symbol": "SheetTransitionCover.half",
      "symbol_kind": "source.lang.swift.decl.enumelement",
      "warning": "undocumented"
    },
    {
      "file": "/Users/lchen/kin-ios/KinUX/KinUX/Src/Presentation/KinPresentationController.swift",
      "line": 16,
      "symbol": "SheetTransitionCover.most",
      "symbol_kind": "source.lang.swift.decl.enumelement",
      "warning": "undocumented"
    },
    {
      "file": "/Users/lchen/kin-ios/KinUX/KinUX/Src/Presentation/KinPresentationController.swift",
      "line": 17,
      "symbol": "SheetTransitionCover.all",
      "symbol_kind": "source.lang.swift.decl.enumelement",
      "warning": "undocumented"
    },
    {
      "file": "/Users/lchen/kin-ios/KinUX/KinUX/Src/Presentation/KinPresentationController.swift",
      "line": 46,
      "symbol": "KinPresentationController",
      "symbol_kind": "source.lang.swift.decl.class",
      "warning": "undocumented"
    },
    {
      "file": "/Users/lchen/kin-ios/KinUX/KinUX/Src/Presentation/KinPresentationController.swift",
      "line": 50,
      "symbol": "KinPresentationController.presentedView",
      "symbol_kind": "source.lang.swift.decl.var.instance",
      "warning": "undocumented"
    },
    {
      "file": "/Users/lchen/kin-ios/KinUX/KinUX/Src/Presentation/KinPresentationController.swift",
      "line": 58,
      "symbol": "KinPresentationController.presentationTransitionDidEnd(_:)",
      "symbol_kind": "source.lang.swift.decl.function.method.instance",
      "warning": "undocumented"
    },
    {
      "file": "/Users/lchen/kin-ios/KinUX/KinUX/Src/Presentation/KinPresentationController.swift",
      "line": 63,
      "symbol": "KinPresentationController.dismissalTransitionWillBegin()",
      "symbol_kind": "source.lang.swift.decl.function.method.instance",
      "warning": "undocumented"
    },
    {
      "file": "/Users/lchen/kin-ios/KinUX/KinUX/Src/Presentation/KinPresentationController.swift",
      "line": 68,
      "symbol": "KinPresentationController.containerViewDidLayoutSubviews()",
      "symbol_kind": "source.lang.swift.decl.function.method.instance",
      "warning": "undocumented"
    },
    {
      "file": "/Users/lchen/kin-ios/KinUX/KinUX/Src/Presentation/KinPresentationController.swift",
      "line": 75,
      "symbol": "SheetPresentationController",
      "symbol_kind": "source.lang.swift.decl.class",
      "warning": "undocumented"
    },
    {
      "file": "/Users/lchen/kin-ios/KinUX/KinUX/Src/Presentation/KinPresentationController.swift",
      "line": 79,
      "symbol": "SheetPresentationController.frameOfPresentedViewInContainerView",
      "symbol_kind": "source.lang.swift.decl.var.instance",
      "warning": "undocumented"
    },
    {
      "file": "/Users/lchen/kin-ios/KinUX/KinUX/Src/Presentation/KinPresentationController.swift",
      "line": 89,
      "symbol": "SheetPresentationController.containerViewDidLayoutSubviews()",
      "symbol_kind": "source.lang.swift.decl.function.method.instance",
      "warning": "undocumented"
    },
    {
      "file": "/Users/lchen/kin-ios/KinUX/KinUX/Src/Presentation/KinPresentationController.swift",
      "line": 102,
      "symbol": "SheetPresentationController.presentationTransitionWillBegin()",
      "symbol_kind": "source.lang.swift.decl.function.method.instance",
      "warning": "undocumented"
    },
    {
      "file": "/Users/lchen/kin-ios/KinUX/KinUX/Src/Presentation/KinPresentationController.swift",
      "line": 112,
      "symbol": "SheetPresentationController.dismissalTransitionWillBegin()",
      "symbol_kind": "source.lang.swift.decl.function.method.instance",
      "warning": "undocumented"
    },
    {
      "file": "/Users/lchen/kin-ios/KinUX/KinUX/Src/Presentation/KinPresentationController.swift",
      "line": 122,
      "symbol": "SheetTransition",
      "symbol_kind": "source.lang.swift.decl.class",
      "warning": "undocumented"
    },
    {
      "file": "/Users/lchen/kin-ios/KinUX/KinUX/Src/Presentation/KinPresentationController.swift",
      "line": 128,
      "symbol": "SheetTransition.presentationController(forPresented:presenting:source:)",
      "symbol_kind": "source.lang.swift.decl.function.method.instance",
      "warning": "undocumented"
    },
    {
      "file": "/Users/lchen/kin-ios/KinUX/KinUX/Src/Presentation/KinPresentationController.swift",
      "line": 134,
      "symbol": "SheetTransition.init(covering:)",
      "symbol_kind": "source.lang.swift.decl.function.method.instance",
      "warning": "undocumented"
    },
    {
      "file": "/Users/lchen/kin-ios/KinUX/KinUX/Src/Presentation/KinPresentationController.swift",
      "line": 138,
      "symbol": "SheetTransition.transitionDuration(using:)",
      "symbol_kind": "source.lang.swift.decl.function.method.instance",
      "warning": "undocumented"
    },
    {
      "file": "/Users/lchen/kin-ios/KinUX/KinUX/Src/Presentation/KinPresentationController.swift",
      "line": 142,
      "symbol": "SheetTransition.animateTransition(using:)",
      "symbol_kind": "source.lang.swift.decl.function.method.instance",
      "warning": "undocumented"
    },
    {
      "file": "/Users/lchen/kin-ios/KinUX/KinUX/Src/Presentation/KinPresentationController.swift",
      "line": 187,
      "symbol": "SheetTransition.animationController(forPresented:presenting:source:)",
      "symbol_kind": "source.lang.swift.decl.function.method.instance",
      "warning": "undocumented"
    },
    {
      "file": "/Users/lchen/kin-ios/KinUX/KinUX/Src/Presentation/KinPresentationController.swift",
      "line": 192,
      "symbol": "SheetTransition.animationController(forDismissed:)",
      "symbol_kind": "source.lang.swift.decl.function.method.instance",
      "warning": "undocumented"
    },
    {
      "file": "/Users/lchen/kin-ios/KinUX/KinUX/Src/Utils/Extensions.swift",
      "line": 14,
      "symbol": "Bundle.kinUx()",
      "symbol_kind": "source.lang.swift.decl.function.method.class",
      "warning": "undocumented"
    },
    {
      "file": "/Users/lchen/kin-ios/KinUX/KinUX/Src/Utils/Extensions.swift",
      "line": 20,
      "symbol": "Invoice.displayable",
      "symbol_kind": "source.lang.swift.decl.var.instance",
      "warning": "undocumented"
    },
    {
      "file": "/Users/lchen/kin-ios/KinUX/KinUX/Src/Utils/Extensions.swift",
      "line": 28,
      "symbol": "LineItem.displayable",
      "symbol_kind": "source.lang.swift.decl.var.instance",
      "warning": "undocumented"
    },
    {
      "file": "/Users/lchen/kin-ios/KinUX/KinUX/Src/ViewModel/ViewModelType.swift",
      "line": 11,
      "symbol": "StateListener",
      "symbol_kind": "source.lang.swift.decl.typealias",
      "warning": "undocumented"
    },
    {
      "file": "/Users/lchen/kin-ios/KinUX/KinUX/Src/ViewModel/ViewModelType.swift",
      "line": 13,
      "symbol": "ObservableViewModelType",
      "symbol_kind": "source.lang.swift.decl.protocol",
      "warning": "undocumented"
    },
    {
      "file": "/Users/lchen/kin-ios/KinUX/KinUX/Src/ViewModel/ViewModelType.swift",
      "line": 14,
      "symbol": "ObservableViewModelType.StateType",
      "symbol_kind": "source.lang.swift.decl.associatedtype",
      "warning": "undocumented"
    },
    {
      "file": "/Users/lchen/kin-ios/KinUX/KinUX/Src/ViewModel/ViewModelType.swift",
      "line": 16,
      "symbol": "ObservableViewModelType.addStateUpdateListener(_:)",
      "symbol_kind": "source.lang.swift.decl.function.method.instance",
      "warning": "undocumented"
    },
    {
      "file": "/Users/lchen/kin-ios/KinUX/KinUX/Src/ViewModel/ViewModelType.swift",
      "line": 18,
      "symbol": "ObservableViewModelType.removeAllListeners()",
      "symbol_kind": "source.lang.swift.decl.function.method.instance",
      "warning": "undocumented"
    },
    {
      "file": "/Users/lchen/kin-ios/KinUX/KinUX/Src/ViewModel/ViewModelType.swift",
      "line": 21,
      "symbol": "ViewModelType",
      "symbol_kind": "source.lang.swift.decl.protocol",
      "warning": "undocumented"
    },
    {
      "file": "/Users/lchen/kin-ios/KinUX/KinUX/Src/ViewModel/ViewModelType.swift",
      "line": 22,
      "symbol": "ViewModelType.ArgsType",
      "symbol_kind": "source.lang.swift.decl.associatedtype",
      "warning": "undocumented"
    },
    {
      "file": "/Users/lchen/kin-ios/KinUX/KinUX/Src/ViewModel/ViewModelType.swift",
      "line": 23,
      "symbol": "ViewModelType.StateType",
      "symbol_kind": "source.lang.swift.decl.associatedtype",
      "warning": "undocumented"
    },
    {
      "file": "/Users/lchen/kin-ios/KinUX/KinUX/Src/ViewModel/ViewModelType.swift",
      "line": 25,
      "symbol": "ViewModelType.cleanup()",
      "symbol_kind": "source.lang.swift.decl.function.method.instance",
      "warning": "undocumented"
    },
    {
      "file": "/Users/lchen/kin-ios/KinUX/KinUX/Src/ViewModel/ViewModelType.swift",
      "line": 28,
      "symbol": "BaseObservableViewModel",
      "symbol_kind": "source.lang.swift.decl.class",
      "warning": "undocumented"
    },
    {
      "file": "/Users/lchen/kin-ios/KinUX/KinUX/Src/ViewModel/ViewModelType.swift",
      "line": 30,
      "symbol": "BaseObservableViewModel.StateType",
      "symbol_kind": "source.lang.swift.decl.typealias",
      "warning": "undocumented"
    },
    {
      "file": "/Users/lchen/kin-ios/KinUX/KinUX/Src/ViewModel/ViewModelType.swift",
      "line": 35,
      "symbol": "BaseObservableViewModel.init()",
      "symbol_kind": "source.lang.swift.decl.function.method.instance",
      "warning": "undocumented"
    },
    {
      "file": "/Users/lchen/kin-ios/KinUX/KinUX/Src/ViewModel/ViewModelType.swift",
      "line": 50,
      "symbol": "BaseObservableViewModel.addStateUpdateListener(_:)",
      "symbol_kind": "source.lang.swift.decl.function.method.instance",
      "warning": "undocumented"
    },
    {
      "file": "/Users/lchen/kin-ios/KinUX/KinUX/Src/ViewModel/ViewModelType.swift",
      "line": 55,
      "symbol": "BaseObservableViewModel.removeAllListeners()",
      "symbol_kind": "source.lang.swift.decl.function.method.instance",
      "warning": "undocumented"
    },
    {
      "file": "/Users/lchen/kin-ios/KinUX/KinUX/Src/ViewModel/ViewModelType.swift",
      "line": 59,
      "symbol": "BaseObservableViewModel.updateState(updater:)",
      "symbol_kind": "source.lang.swift.decl.function.method.instance",
      "warning": "undocumented"
    },
    {
      "file": "/Users/lchen/kin-ios/KinUX/KinUX/Src/ViewModel/ViewModelType.swift",
      "line": 72,
      "symbol": "BaseObservableViewModel.getDefaultState()",
      "symbol_kind": "source.lang.swift.decl.function.method.instance",
      "warning": "undocumented"
    },
    {
      "file": "/Users/lchen/kin-ios/KinUX/KinUX/Src/ViewModel/ViewModelType.swift",
      "line": 76,
      "symbol": "BaseObservableViewModel.onStateUpdated(_:)",
      "symbol_kind": "source.lang.swift.decl.function.method.instance",
      "warning": "undocumented"
    },
    {
      "file": "/Users/lchen/kin-ios/KinUX/KinUX/Src/ViewModel/ViewModelType.swift",
      "line": 81,
      "symbol": "BaseViewModel",
      "symbol_kind": "source.lang.swift.decl.class",
      "warning": "undocumented"
    },
    {
      "file": "/Users/lchen/kin-ios/KinUX/KinUX/Src/ViewModel/ViewModelType.swift",
      "line": 82,
      "symbol": "BaseViewModel.ArgsType",
      "symbol_kind": "source.lang.swift.decl.typealias",
      "warning": "undocumented"
    },
    {
      "file": "/Users/lchen/kin-ios/KinUX/KinUX/Src/ViewModel/ViewModelType.swift",
      "line": 83,
      "symbol": "BaseViewModel.StateType",
      "symbol_kind": "source.lang.swift.decl.typealias",
      "warning": "undocumented"
    },
    {
      "file": "/Users/lchen/kin-ios/KinUX/KinUX/Src/ViewModel/ViewModelType.swift",
      "line": 85,
      "symbol": "BaseViewModel.cleanup()",
      "symbol_kind": "source.lang.swift.decl.function.method.instance",
      "warning": "undocumented"
    },
    {
      "file": "/Users/lchen/kin-ios/KinUX/KinUX/Src/ViewModel/ViewModelType.swift",
      "line": 90,
      "symbol": "Navigator",
      "symbol_kind": "source.lang.swift.decl.protocol",
      "warning": "undocumented"
    }
  ],
  "source_directory": "/Users/lchen/kin-ios"
}